playmobile/__init__.py
playmobile/abstract.py
playmobile/client.py
playmobile/entities.py
playmobile/exceptions.py
playmobile/test_utils.py
playmobile_client-1.0.0.dist-info/LICENSE.md
playmobile_client-1.0.0.dist-info/WHEEL
playmobile_client-1.0.0.dist-info/METADATA
playmobile_client-1.0.0.dist-info/RECORD
