Metadata-Version: 2.1
Name: playmobile-client
Version: 1.0.0
Summary: Python client for Playmobile.uz API
Home-page: https://github.com/absolutionsuz/playmobile-client
License: BSD-3-Clause
Keywords: playmobile,smsxabar,client,httpx,requests
Author: Daniil Andreev
Author-email: dandreevv22@gmail.com
Requires-Python: >=3.7,<4.0
Classifier: Development Status :: 4 - Beta
Classifier: Environment :: Web Environment
Classifier: Framework :: AsyncIO
Classifier: Intended Audience :: Developers
Classifier: License :: OSI Approved :: BSD License
Classifier: Operating System :: OS Independent
Classifier: Programming Language :: Python :: 3
Classifier: Programming Language :: Python :: 3.7
Classifier: Programming Language :: Python :: 3.8
Classifier: Programming Language :: Python :: 3.9
Classifier: Programming Language :: Python :: 3.10
Classifier: Programming Language :: Python :: 3.11
Classifier: Programming Language :: Python :: 3 :: Only
Classifier: Topic :: Internet :: WWW/HTTP
Classifier: Topic :: Software Development :: Libraries :: Python Modules
Requires-Dist: attrs (>=22.0,<23.0)
Requires-Dist: faker (>=16.6,<17.0)
Requires-Dist: httpx (>=0.23,<0.24)
Requires-Dist: marshmallow (>=3.18,<4.0)
Project-URL: Repository, https://github.com/absolutionsuz/playmobile-client
